trio_engineio/__init__.py
trio_engineio/_ssl.py
trio_engineio/eio_types.py
trio_engineio/exceptions.py
trio_engineio/packet.py
trio_engineio/payload.py
trio_engineio/py.typed
trio_engineio/trio_client.py
trio_engineio/trio_util.py
trio_engineio-0.2.0.dist-info/LICENSE
trio_engineio-0.2.0.dist-info/METADATA
trio_engineio-0.2.0.dist-info/WHEEL
trio_engineio-0.2.0.dist-info/RECORD
