Metadata-Version: 2.1
Name: trio-engineio
Version: 0.2.0
Summary: An asynchronous Engine.IO client using the trio framework
Home-page: https://github.com/Elmeric/trio-engineio
License: BSD-3-Clause
Author: Eric Lemoine
Author-email: erik.lemoine@gmail.com
Requires-Python: >=3.9.0,<4.0.0
Classifier: Environment :: Web Environment
Classifier: Framework :: Trio
Classifier: Intended Audience :: Developers
Classifier: License :: OSI Approved :: BSD License
Classifier: Natural Language :: English
Classifier: Operating System :: OS Independent
Classifier: Programming Language :: Python :: 3
Classifier: Programming Language :: Python :: 3.9
Classifier: Programming Language :: Python :: 3.10
Classifier: Programming Language :: Python :: 3.11
Classifier: Programming Language :: Python :: 3.12
Classifier: Topic :: Software Development :: Libraries
Requires-Dist: httpcore (>=0.17.1,<0.18.0)
Requires-Dist: trio (>=0.22.0,<0.23.0)
Requires-Dist: trio-websocket (>=0.10.2,<0.11.0)
Requires-Dist: typing-extensions (>=4.4.0,<5.0.0) ; python_version < "3.8"
Project-URL: Documentation, https://elmeric.github.io/trio-engineio
Project-URL: Repository, https://github.com/Elmeric/trio-engineio
